{
    "virgil": {
        "type": "sequential",
        "offset": [0, -20],
        "origin": [0.5, 0.5],
        "phrases": [
            "Welcome to Greed."
        ],
        "style": { 
            "fontSize": "24px", 
            "fontFamily": "Courier",
            "fontStyle": "bold",
            "wrap": {
                 "width": 400, 
                 "mode": "word"
             },
            "align": "center", 
            "color": "#e3e3e3",
            "backgroundColor": "#000000"
        },
        "padding": {
            "x": 7.5,
            "y": 5
        }
    },
    "saver1": {
        "type": "click",
        "offset": [0, -20],
        "origin": [0.5, 0.5],
        "phrases": [
            "Why spend?",
            "Why waste?"
        ],
        "style": { 
            "fontSize": "24px", 
            "fontFamily": "Courier",
            "fontStyle": "bold",
            "wrap": {
                 "width": 400, 
                  "mode": "word"
             },
            "align": "center", 
            "color": "#e3e3e3",
            "backgroundColor": "#000000"
        },
        
        "padding": {
            "x": 7.5,
            "y": 5
        }
    },
    "saver2": {
        "type": "click",
        "offset": [0, -20],
        "origin": [0.5, 0.5],
        "phrases": [
            "Why spend?",
            "Why waste?"
        ],
        "style": { 
            "fontSize": "24px", 
            "fontFamily": "Courier",
            "fontStyle": "bold",
            "wrap": {
                 "width": 400, 
                  "mode": "word"
             },
            "align": "center", 
            "color": "#e3e3e3",
            "backgroundColor": "#000000"
        },
        
        "padding": {
            "x": 7.5,
            "y": 5
        }
    },

    "spender1": {
        "type": "click",
        "offset": [0, -20],
        "origin": [0.5, 0.5],
        "phrases": [
            "Why save?"
        ],
        "style": { 
            "fontSize": "24px", 
            "fontFamily": "Courier",
            "fontStyle": "bold",
            "wrap": {
                 "width": 400, 
                  "mode": "word"
             },
            "align": "center", 
            "color": "#e3e3e3",
            "backgroundColor": "#000000"
        },
        
        "padding": {
            "x": 7.5,
            "y": 5
        }
    },

    "spender2": {
        "type": "click",
        "offset": [0, -20],
        "origin": [0.5, 0.5],
        "phrases": [
            "Why save?"
        ],
        "style": { 
            "fontSize": "24px", 
            "fontFamily": "Courier",
            "fontStyle": "bold",
            "wrap": {
                 "width": 400, 
                  "mode": "word"
             },
            "align": "center", 
            "color": "#e3e3e3",
            "backgroundColor": "#000000"
        },
        
        "padding": {
            "x": 7.5,
            "y": 5
        }
    }

}