{ "compressionlevel":-1,
 "editorsettings":
    {
     "export":
        {
         "format":"json",
         "target":"level10_treachery.json"
        }
    },
 "height":5,
 "infinite":false,
 "layers":[
        {
         "draworder":"topdown",
         "id":11,
         "name":"background",
         "objects":[
                {
                 "gid":130,
                 "height":652.4,
                 "id":289,
                 "name":"",
                 "rotation":0,
                 "type":"",
                 "visible":true,
                 "width":2364,
                 "x":-271,
                 "y":528
                }],
         "opacity":1,
         "type":"objectgroup",
         "visible":true,
         "x":0,
         "y":0
        }, 
        {
         "draworder":"topdown",
         "id":12,
         "name":"background_objects_2",
         "objects":[
                {
                 "gid":126,
                 "height":426,
                 "id":290,
                 "name":"",
                 "rotation":0,
                 "type":"",
                 "visible":true,
                 "width":834.157,
                 "x":-142.333,
                 "y":496.667
                }],
         "opacity":1,
         "type":"objectgroup",
         "visible":true,
         "x":0,
         "y":0
        }, 
        {
         "draworder":"topdown",
         "id":13,
         "name":"background_objects_1",
         "objects":[
                {
                 "gid":125,
                 "height":540,
                 "id":291,
                 "name":"",
                 "rotation":0,
                 "type":"",
                 "visible":true,
                 "width":996,
                 "x":801,
                 "y":528
                }, 
                {
                 "gid":129,
                 "height":128,
                 "id":292,
                 "name":"",
                 "rotation":0,
                 "type":"",
                 "visible":true,
                 "width":2560,
                 "x":-25,
                 "y":529
                }],
         "opacity":1,
         "type":"objectgroup",
         "visible":true,
         "x":0,
         "y":0
        }, 
        {
         "data":[0, 0, 0, 0, 0, 0, 0, 0, 0, 0, 0, 0, 0, 0, 0, 0, 0, 0, 0, 0, 0, 0, 0, 0, 0, 0, 0, 0, 0, 0, 0, 0, 0, 0, 0, 0, 0, 0, 0, 0, 0, 0, 0, 0, 0, 0, 0, 0, 0, 0, 0, 0, 0, 0, 0, 0, 0, 0, 0, 0, 19, 19, 19, 19, 19, 19, 19, 19, 19, 19, 19, 19, 19, 19, 19],
         "height":5,
         "id":8,
         "name":"ground",
         "opacity":1,
         "type":"tilelayer",
         "visible":true,
         "width":15,
         "x":0,
         "y":0
        }, 
        {
         "draworder":"topdown",
         "id":4,
         "name":"game",
         "objects":[
                {
                 "gid":132,
                 "height":192,
                 "id":73,
                 "name":"virgil",
                 "rotation":0,
                 "type":"",
                 "visible":true,
                 "width":120,
                 "x":139,
                 "y":508
                }, 
                {
                 "gid":142,
                 "height":350,
                 "id":80,
                 "name":"elevator",
                 "rotation":0,
                 "type":"",
                 "visible":true,
                 "width":375,
                 "x":1735.75,
                 "y":514.346
                }, 
                {
                 "gid":136,
                 "height":192,
                 "id":84,
                 "name":"player",
                 "rotation":0,
                 "type":"",
                 "visible":true,
                 "width":120,
                 "x":8.167,
                 "y":507.167
                }, 
                {
                 "gid":156,
                 "height":355,
                 "id":92,
                 "name":"elevator_doors",
                 "rotation":0,
                 "type":"elevator_doors",
                 "visible":true,
                 "width":375,
                 "x":1735.75,
                 "y":517.013
                }, 
                {
                 "gid":124,
                 "height":172,
                 "id":294,
                 "name":"brut",
                 "properties":[
                        {
                         "name":"clickable",
                         "type":"bool",
                         "value":true
                        }],
                 "rotation":0,
                 "type":"",
                 "visible":true,
                 "width":86,
                 "x":1383,
                 "y":512
                }, 
                {
                 "gid":128,
                 "height":172,
                 "id":295,
                 "name":"cassius",
                 "properties":[
                        {
                         "name":"clickable",
                         "type":"bool",
                         "value":true
                        }],
                 "rotation":0,
                 "type":"",
                 "visible":true,
                 "width":86,
                 "x":1511,
                 "y":512
                }, 
                {
                 "gid":127,
                 "height":191,
                 "id":296,
                 "name":"judas",
                 "properties":[
                        {
                         "name":"clickable",
                         "type":"bool",
                         "value":true
                        }],
                 "rotation":0,
                 "type":"",
                 "visible":true,
                 "width":98,
                 "x":871,
                 "y":512
                }],
         "opacity":1,
         "type":"objectgroup",
         "visible":true,
         "x":0,
         "y":0
        }],
 "nextlayerid":14,
 "nextobjectid":297,
 "orientation":"orthogonal",
 "renderorder":"right-down",
 "tiledversion":"2021.01.13",
 "tileheight":128,
 "tilesets":[
        {
         "columns":1,
         "firstgid":1,
         "image":"..\/assets\/tileset.png",
         "imageheight":2560,
         "imagewidth":128,
         "margin":0,
         "name":"tiles",
         "spacing":0,
         "tilecount":20,
         "tileheight":128,
         "tiles":[
                {
                 "id":0,
                 "properties":[
                        {
                         "name":"collide",
                         "type":"bool",
                         "value":true
                        }]
                }],
         "tilewidth":128
        }, 
        {
         "columns":0,
         "firstgid":21,
         "grid":
            {
             "height":1,
             "orientation":"orthogonal",
             "width":1
            },
         "margin":0,
         "name":"background",
         "spacing":0,
         "tilecount":8,
         "tileheight":896,
         "tiles":[
                {
                 "id":103,
                 "image":"..\/assets\/level10_treachery\/brut.png",
                 "imageheight":172,
                 "imagewidth":86
                }, 
                {
                 "id":104,
                 "image":"..\/assets\/level10_treachery\/devil.png",
                 "imageheight":540,
                 "imagewidth":996
                }, 
                {
                 "id":105,
                 "image":"..\/assets\/level10_treachery\/feet.png",
                 "imageheight":764,
                 "imagewidth":1496
                }, 
                {
                 "id":106,
                 "image":"..\/assets\/level10_treachery\/judas.png",
                 "imageheight":191,
                 "imagewidth":98
                }, 
                {
                 "id":107,
                 "image":"..\/assets\/level10_treachery\/cassius.png",
                 "imageheight":172,
                 "imagewidth":86
                }, 
                {
                 "id":108,
                 "image":"..\/assets\/level10_treachery\/strip_treachery.png",
                 "imageheight":128,
                 "imagewidth":2560
                }, 
                {
                 "id":109,
                 "image":"..\/assets\/level10_treachery\/background.png",
                 "imageheight":896,
                 "imagewidth":2560
                }, 
                {
                 "id":110,
                 "image":"..\/assets\/level10_treachery\/headline.png",
                 "imageheight":130,
                 "imagewidth":796
                }],
         "tilewidth":2560
        }, 
        {
         "columns":1,
         "firstgid":132,
         "grid":
            {
             "height":248,
             "orientation":"orthogonal",
             "width":152
            },
         "image":"..\/assets\/virgil.png",
         "imageheight":768,
         "imagewidth":120,
         "margin":0,
         "name":"virgil",
         "spacing":0,
         "tilecount":4,
         "tileheight":192,
         "tilewidth":120
        }, 
        {
         "columns":1,
         "firstgid":136,
         "grid":
            {
             "height":248,
             "orientation":"orthogonal",
             "width":152
            },
         "image":"..\/assets\/dante.png",
         "imageheight":1152,
         "imagewidth":120,
         "margin":0,
         "name":"dante",
         "spacing":0,
         "tilecount":6,
         "tileheight":192,
         "tilewidth":120
        }, 
        {
         "columns":1,
         "firstgid":142,
         "grid":
            {
             "height":392,
             "orientation":"orthogonal",
             "width":350
            },
         "image":"..\/assets\/elevator.png",
         "imageheight":4900,
         "imagewidth":375,
         "margin":0,
         "name":"elevator",
         "spacing":0,
         "tilecount":14,
         "tileheight":350,
         "tilewidth":375
        }, 
        {
         "columns":1,
         "firstgid":156,
         "grid":
            {
             "height":322,
             "orientation":"orthogonal",
             "width":196
            },
         "image":"..\/assets\/elevator_doors.png",
         "imageheight":3500,
         "imagewidth":375,
         "margin":0,
         "name":"elevator_doors",
         "spacing":0,
         "tilecount":10,
         "tileheight":350,
         "tilewidth":375
        }],
 "tilewidth":128,
 "type":"map",
 "version":1.4,
 "width":15
}